sqlalchemy_utc/__init__.py
sqlalchemy_utc/now.py
sqlalchemy_utc/py.typed
sqlalchemy_utc/sqltypes.py
sqlalchemy_utc/timezone.py
sqlalchemy_utc/version.py
SQLAlchemy_Utc-0.14.0.dist-info/LICENSE
SQLAlchemy_Utc-0.14.0.dist-info/METADATA
SQLAlchemy_Utc-0.14.0.dist-info/WHEEL
SQLAlchemy_Utc-0.14.0.dist-info/top_level.txt
SQLAlchemy_Utc-0.14.0.dist-info/RECORD
